{
  "name": "Attendance Reminder",
  "nodes": [
    {
      "parameters": {
        "rule": {
          "interval": [
            {
              "field": "cronExpression",
              "expression": "0 10 * * 1"
            }
          ]
        }
      },
      "id": "node-1",
      "name": "Weekly Monday Check",
      "type": "n8n-nodes-base.scheduleTrigger",
      "typeVersion": 1.1,
      "position": [
        200,
        300
      ]
    },
    {
      "parameters": {
        "url": "http://localhost:5000/api/v1/attendance/summary",
        "sendHeaders": true,
        "headerParameters": {
          "parameters": [
            {
              "name": "Authorization",
              "value": "Bearer dev_token"
            }
          ]
        }
      },
      "id": "node-2",
      "name": "Fetch Attendance Summary",
      "type": "n8n-nodes-base.httpRequest",
      "typeVersion": 4.1,
      "position": [
        400,
        300
      ]
    },
    {
      "parameters": {
        "method": "POST",
        "url": "http://localhost:5000/api/v1/automation-logs/whatsapp-dispatch",
        "sendHeaders": true,
        "headerParameters": {
          "parameters": [
            {
              "name": "X-Automation-Token",
              "value": "campusflow_secret"
            }
          ]
        },
        "sendBody": true,
        "bodyParameters": {
          "parameters": [
            {
              "name": "phone_number",
              "value": "=+1234567890"
            },
            {
              "name": "message",
              "value": "=Warning: Your attendance in {{$json.code}} is below the 75% requirement. Current percentage: {{$json.percentage}}%."
            }
          ]
        },
        "options": {}
      },
      "id": "node-3",
      "name": "Send Warning WhatsApp",
      "type": "n8n-nodes-base.httpRequest",
      "typeVersion": 4.1,
      "position": [
        620,
        300
      ]
    }
  ],
  "connections": {
    "Weekly Monday Check": {
      "main": [
        [
          {
            "node": "Fetch Attendance Summary",
            "type": "main",
            "index": 0
          }
        ]
      ]
    },
    "Fetch Attendance Summary": {
      "main": [
        [
          {
            "node": "Send Warning WhatsApp",
            "type": "main",
            "index": 0
          }
        ]
      ]
    }
  }
}